mypythonlib/__init__.py
mypythonlib/myfunctions.py
mypythonlibpooja-0.1.0.dist-info/METADATA
mypythonlibpooja-0.1.0.dist-info/WHEEL
mypythonlibpooja-0.1.0.dist-info/top_level.txt
mypythonlibpooja-0.1.0.dist-info/RECORD
