Metadata-Version: 2.1
Name: mypythonlibpooja
Version: 0.1.0
Summary: My first Python library
Home-page: https://mypythonlibpooja.readthedocs.io/
Author: Me
License: MIT
Platform: UNKNOWN
